fastapi_simple_oidc/__init__.py
fastapi_simple_oidc/main.py
fastapi_simple_oidc/quick_test.py
fastapi_simple_oidc/settings.py
fastapi_simple_oidc-0.0.4.dist-info/METADATA
fastapi_simple_oidc-0.0.4.dist-info/WHEEL
fastapi_simple_oidc-0.0.4.dist-info/top_level.txt
fastapi_simple_oidc-0.0.4.dist-info/RECORD
