Metadata-Version: 2.2
Name: fastapi_simple_oidc
Version: 0.0.4
Summary: OIDC for FastAPI
Project-URL: Homepage, https://github.com/levy42/fastapi-simple-oidc
Project-URL: Repository, https://github.com/levy42/fastapi-simple-oidc
Keywords: fastapi,sso
Requires-Dist: authlib>=1.4.1
Requires-Dist: fastapi
Requires-Dist: itsdangerous>=2.2.0
Requires-Dist: pydantic>=2
Requires-Dist: pydantic-settings
Provides-Extra: test
Requires-Dist: pytest; extra == "test"
Requires-Dist: uvicorn; extra == "test"
